Workbook

Sheet Dashboard
A1: Delta Cleaning — Operations & Finance Dashboard
A2: Snapshot from live data · 28 June 2026 · figures recalculate if you edit the Clients / Monthly P&L tabs
B4: Active clients | E4: Monthly recurring (MRR)
B5: =COUNTIF(Clients!C5:C14,"Active") -> 9 | E5: =SUMIF(Clients!C5:C14,"Active",Clients!G5:G14) -> 11275.39
B7: Annual run-rate | E7: Monthly profit (active)
B8: =SUMIF(Clients!C5:C14,"Active",Clients!H5:H14) -> 135304.68 | E8: =SUMIF(Clients!C5:C14,"Active",Clients!I5:I14) -> 5149.67
B10: Avg margin (active) | E10: Last month income (Jun)
B11: =IFERROR(SUMIF(Clients!C5:C14,"Active",Clients!I5:I14)/SUMIF(Clients!C5:C14,"Active",Clients!G5:G14),0) -> 0.45671768 | E11: ='Monthly P&L'!B8 -> 10340
B14: Top clients by monthly value
B15: Client | C15: Monthly | D15: Margin
B16: =Clients!A5 -> MyLocalDoc | C16: =Clients!G5 -> 3079.99 | D16: =Clients!J5 -> 0.48051779
B17: =Clients!A6 -> Chase Commercial | C17: =Clients!G6 -> 2177.07 | D17: =Clients!J6 -> 0.40286716
B18: =Clients!A7 -> RayWhite Redcliffe | C18: =Clients!G7 -> 1690 | D18: =Clients!J7 -> 0.38461538
B19: =Clients!A8 -> Slate Property | C19: =Clients!G8 -> 975 | D19: =Clients!J8 -> 0.65055385
B20: =Clients!A9 -> Nova Systems | C20: =Clients!G9 -> 823.33 | D20: =Clients!J9 -> 0.44736618

Sheet Clients
A1: Client Book
A2: Source: Supabase clients table · 28 Jun 2026. Margin is computed (profit ÷ value).
A4: Client | B4: State | C4: Status | D4: Service | E4: Frequency | F4: Visits/mo | G4: Monthly Value | H4: Annual Value | I4: Monthly Profit | J4: Margin
A5: MyLocalDoc | B5: QLD | C5: Active | D5: General, Floor care | E5: Monthly | F5: 1 | G5: 3079.99 | H5: 36959.88 | I5: 1479.99 | J5: =IFERROR(I5/G5,0) -> 0.48051779
A6: Chase Commercial | B6: QLD | C6: Active | D6: General | E6: — | F6: 0 | G6: 2177.07 | H6: 26124.84 | I6: 877.07 | J6: =IFERROR(I6/G6,0) -> 0.40286716
A7: RayWhite Redcliffe | B7: QLD | C7: Active | D7: General, Window | E7: Weekly | F7: 4.333 | G7: 1690 | H7: 20280 | I7: 650 | J7: =IFERROR(I7/G7,0) -> 0.38461538
A8: Slate Property | B8: QLD | C8: Active | D8: General | E8: — | F8: 1 | G8: 975 | H8: 11700 | I8: 634.29 | J8: =IFERROR(I8/G8,0) -> 0.65055385
A9: Nova Systems | B9: QLD | C9: Active | D9: General | E9: Weekly | F9: 4.333 | G9: 823.33 | H9: 9879.96 | I9: 368.33 | J9: =IFERROR(I9/G9,0) -> 0.44736618
A10: Mitchelton Dental Care | B10: QLD | C10: Active | D10: General | E10: Monthly | F10: 1 | G10: 820 | H10: 9840 | I10: 330 | J10: =IFERROR(I10/G10,0) -> 0.40243902
A11: Parkside Group | B11: QLD | C11: Active | D11: General | E11: Weekly | F11: 4.333 | G11: 650 | H11: 7800 | I11: 270.83 | J11: =IFERROR(I11/G11,0) -> 0.41666154
A12: Seam Spatial | B12: QLD | C12: Active | D12: General | E12: Weekly | F12: 4.333 | G12: 650 | H12: 7800 | I12: 270.83 | J12: =IFERROR(I12/G12,0) -> 0.41666154
A13: 15 Felix Street | B13: QLD | C13: Active | D13: Pressure washing | E13: Quarterly | F13: 0.333 | G13: 410 | H13: 4920 | I13: 268.33 | J13: =IFERROR(I13/G13,0) -> 0.65446341
A14: Griffin National Realestate | B14: QLD | C14: Inactive | D14: General, Window | E14: Fortnightly | F14: 2.167 | G14: 303.33 | H14: 3639.96 | I14: 130 | J14: =IFERROR(I14/G14,0) -> 0.42857614
A15: TOTAL (all clients) | G15: =SUM(G5:G14) -> 11578.72 | H15: =SUM(H5:H14) -> 138944.64 | I15: =SUM(I5:I14) -> 5279.67 | J15: =IFERROR(I15/G15,0) -> 0.45598045

Sheet Monthly P&L
A1: Monthly Profit & Loss (approved Xero transactions)
A2: Source: Supabase xero_approved_transactions · 28 Jun 2026. Net = Income − Expense.
A4: Month | B4: Income | C4: Expense | D4: Net
A5: Nov 2024 | B5: 250 | C5: 154 | D5: =B5-C5 -> 96
A6: Apr 2026 | B6: 2519 | C6: 0 | D6: =B6-C6 -> 2519
A7: May 2026 | B7: 10712.9 | C7: 0 | D7: =B7-C7 -> 10712.9
A8: Jun 2026 | B8: 10340 | C8: 0 | D8: =B8-C8 -> 10340
A9: TOTAL | B9: =SUM(B5:B8) -> 23821.9 | C9: =SUM(C5:C8) -> 154 | D9: =SUM(D5:D8) -> 23667.9
